connect/__init__.py
connect/artist.py
connect/client.py
connect/errors.py
connect/http.py
connect/playlist.py
connect/release.py
connect/track.py
connect/utils.py
connect.py-0.4.2.dist-info/DESCRIPTION.rst
connect.py-0.4.2.dist-info/METADATA
connect.py-0.4.2.dist-info/RECORD
connect.py-0.4.2.dist-info/WHEEL
connect.py-0.4.2.dist-info/metadata.json
connect.py-0.4.2.dist-info/top_level.txt
tests/__init__.py
tests/test_get_all_catalog.py
tests/test_get_catalog.py
tests/test_search.py
