Metadata-Version: 2.0
Name: connect.py
Version: 0.4.2
Summary: An API wrapper for Monstercat Connect written in Python.
Home-page: https://github.com/GiovanniMCMXCIX/connect.py
Author: GiovanniMCMXCIX
Author-email: irimea.giovani.9@gmail.com
License: MIT
Platform: UNKNOWN
Classifier: Development Status :: 4 - Beta
Classifier: License :: OSI Approved :: MIT License
Classifier: Intended Audience :: Developers
Classifier: Natural Language :: English
Classifier: Operating System :: OS Independent
Classifier: Programming Language :: Python :: 3 :: Only
Classifier: Programming Language :: Python :: 3.6
Classifier: Topic :: Internet
Classifier: Topic :: Software Development :: Libraries
Classifier: Topic :: Software Development :: Libraries :: Python Modules
Classifier: Topic :: Utilities
Requires-Dist: requests (>=2.18.4)
Provides-Extra: performance
Requires-Dist: ujson (>=1.35); extra == 'performance'
